{
    "dte": [
        {
            "date": " Guatemala, 15/01/2021 15:25 hrs. ",
            "reference": " W4239884 ",
            "emmiter_nit": " 7378106 ",
            "reciever_nit": " 8338817 ",
            "value": " 100.00 ",
            "tax": " 12.00 ",
            "total": " 112.00 "
        },
        {
            "date": " Guatemala, 15/01/2021 15:25 hrs. ",
            "reference": " W4239884 ",
            "emmiter_nit": " 8338817 ",
            "reciever_nit": " 7378106 ",
            "value": " 100.00 ",
            "tax": " 12.00 ",
            "total": " 112.00 "
        },
        {
            "date": " Guatemala, 15/01/2021 15:25 hrs. ",
            "reference": " W49467884 ",
            "emmiter_nit": " 7378106 ",
            "reciever_nit": " 8338817 ",
            "value": " 100.00 ",
            "tax": " 12.00 ",
            "total": " 112.00 "
        },
        {
            "date": " Guatemala, 15/01/2021 15:25 hrs. ",
            "reference": " W4965884 ",
            "emmiter_nit": " 2431739K ",
            "reciever_nit": " 7378106 ",
            "value": " 100.00 ",
            "tax": " 12.00 ",
            "total": " 112.00 "
        },
        {
            "date": " Guatemala, 15/01/2021 15:25 hrs. ",
            "reference": " W49345884 ",
            "emmiter_nit": " 2431739K ",
            "reciever_nit": " 7378106 ",
            "value": " 100.00 ",
            "tax": " 12.00 ",
            "total": " 112.00 "
        },
        {
            "date": " Guatemala, 15/01/2021 15:25 hrs. ",
            "reference": " W498345484 ",
            "emmiter_nit": " 8431523 ",
            "reciever_nit": " 2431739K ",
            "value": " 100.00 ",
            "tax": " 12.00 ",
            "total": " 112.00 "
        },
        {
            "date": " Guatemala, 15/01/2021 15:25 hrs. ",
            "reference": " W49884 ",
            "emmiter_nit": " 8431523 ",
            "reciever_nit": " 2431739K ",
            "value": " 100.00 ",
            "tax": " 12.00 ",
            "total": " 112.00 "
        },
        {
            "date": " Guatemala, 24/12/2021 20:00 hrs. ",
            "reference": " A1990 ",
            "emmiter_nit": " 80400442 ",
            "reciever_nit": " 1251425K ",
            "value": " 80.00 ",
            "tax": " 12.00 ",
            "total": " 92.00 "
        },
        {
            "date": " Guatemala, 01/01/2021 15:25 hrs. ",
            "reference": " F784861 ",
            "emmiter_nit": " 5408008 ",
            "reciever_nit": " 43401635 ",
            "value": " 150.75   ",
            "tax": " 18.09 ",
            "total": " 168.84 "
        },
        {
            "date": " Guatemala, 25/12/2021 7:25 hrs. ",
            "reference": " T888888888 ",
            "emmiter_nit": " 8431523 ",
            "reciever_nit": " 2431739K ",
            "value": " 200.00 ",
            "tax": " 24.00 ",
            "total": " 224.00 "
        },
        {
            "date": " Guatemala, 31/10/2021 00:00 hrs. ",
            "reference": " T56488 ",
            "emmiter_nit": " 8431523 ",
            "reciever_nit": " 2431739K ",
            "value": " 5000.00 ",
            "tax": " 600.00 ",
            "total": " 5600.00 "
        },
        {
            "date": " Guatemala, 08/05/2021 15:25 hrs. ",
            "reference": " T5885 ",
            "emmiter_nit": " 2431739K ",
            "reciever_nit": " 8338817 ",
            "value": " 900.00 ",
            "tax": " 108.00 ",
            "total": " 1008.00 "
        }
    ]
}